{"SurveyAttributes":{"SurveyID":"SV_1GoZ6756ZYvbMyh","SurveyName":"Weird Survey Testing","SurveyDescription":null,"SurveyOwnerID":"UR_8kzO7vEaBPWnAB7","SurveyBrandID":"tufts","DivisionID":null,"SurveyLanguage":"EN","SurveyActiveResponseSet":"RS_7U8rlZCdJsk8iZn","SurveyStatus":"Active","SurveyStartDate":"0000-00-00 00:00:00","SurveyExpirationDate":"0000-00-00 00:00:00","SurveyCreationDate":"2016-03-29 13:33:11","CreatorID":"UR_8kzO7vEaBPWnAB7","LastModified":"2016-03-29 14:38:54","LastAccessed":"0000-00-00 00:00:00","LastActivated":"2016-03-29 13:58:06","Deleted":null},"Blocks":[{"Type":"Default","Description":"What's up with feelings, bruh?","ID":"BL_6YHy0Fb9BhTaZb7","BlockElements":[[{"SurveyID":"SV_1GoZ6756ZYvbMyh","Element":"SQ","PrimaryAttribute":"QID1","SecondaryAttribute":"Indicate how you feel today","TertiaryAttribute":null,"Payload":{"QuestionText":"Indicate how you feel today","DataExportTag":"Q1","QuestionType":"MC","Selector":"SAVR","SubSelector":"TX","Configuration":{"QuestionDescriptionOption":"UseText"},"QuestionDescription":"Indicate how you feel today","Choices":{"1":{"Display":"Aggressive"},"2":{"Display":"Anxious","DisplayLogic":{"0":{"0":{"LogicType":"Question","QuestionID":"QID1","QuestionIsInLoop":"no","ChoiceLocator":"q://QID1/SelectableChoice/1","Operator":"Selected","QuestionIDFromLocator":"QID1","LeftOperand":"q://QID1/SelectableChoice/1","Type":"Expression","Description":"<span class=\"ConjDesc\">If</span> <span class=\"QuestionDesc\">Indicate how you feel today</span> <span class=\"LeftOpDesc\">Aggressive</span> Is <span class=\"OpDesc\">Selected</span> "},"Type":"If"},"Type":"BooleanExpression","inPage":false}},"3":{"Display":"Apologetic"},"4":{"Display":"Arrogant"},"5":{"Display":"Bashful"},"6":{"Display":"Blissful"},"7":{"Display":"Bored"},"8":{"Display":"Cautious"},"9":{"Display":"Cold"},"10":{"Display":"Confident"},"11":{"Display":"Curious"},"12":{"Display":"Determined"},"13":{"Display":"Disappointed"},"14":{"Display":"Disgusted"},"15":{"Display":"Hungover af"},"16":{"Display":"Happy"},"17":{"Display":"Optimistic"},"18":{"Display":"Sad"},"19":{"Display":"Surprised"},"20":{"Display":"Suspicious"},"21":{"Display":"Sympathetic"},"22":{"Display":"Thoughtful"},"23":{"Display":"Withdrawn"},"24":{"Display":"Other","TextEntry":"true"}},"ChoiceOrder":[1,2,3,4,5,6,7,8,9,10,11,12,13,14,15,16,17,18,19,20,21,22,23,24],"Validation":{"Settings":{"ForceResponse":"OFF","ForceResponseType":"ON","Type":"None"}},"Language":[],"QuestionID":"QID1"},"Responses":{"Q1":[1,21,6,24,8,5,9,3,8,13,17,8,17,17,8,7,1,5,10,14,14,3,4,17,19,6,6,11,8,16,8,18,3,4,18,11,15,24,8,8,14,20,10,3,3,15],"Q1_TEXT":["","","","Vel dignissim eros pretium elementum! Nec iaculis molestie rutrum aenean eget. Ultricies. Nec sapien convallis.","","","","","","","","","","","","","","","","","","","","","","","","","","","","","","","","","","Fringilla fusce, ac egestas accumsan vivamus eu. Aliquam dolorem. Odio sollicitudin! Scelerisque.","","","","","","","",""]},"Table":{"N":[2,0,5,2,2,3,1,8,1,2,2,0,1,3,2,1,4,2,1,1,1,0,0,2],"Percent":["2.2%","0.0%","5.4%","2.2%","2.2%","3.3%","1.1%","8.7%","1.1%","2.2%","2.2%","0.0%","1.1%","3.3%","2.2%","1.1%","4.3%","2.2%","1.1%","1.1%","1.1%","0.0%","0.0%","2.2%"],"":["Aggressive","Anxious","Apologetic","Arrogant","Bashful","Blissful","Bored","Cautious","Cold","Confident","Curious","Determined","Disappointed","Disgusted","Hungover af","Happy","Optimistic","Sad","Surprised","Suspicious","Sympathetic","Thoughtful","Withdrawn","Other"]}}],[{"SurveyID":"SV_1GoZ6756ZYvbMyh","Element":"SQ","PrimaryAttribute":"QID3","SecondaryAttribute":"Indicate to what extent you identify with the following feelings today:","TertiaryAttribute":null,"Payload":{"QuestionText":"Indicate to what extent you identify with the following feelings today:","DefaultChoices":false,"DataExportTag":"Q3","QuestionType":"Matrix","Selector":"Likert","SubSelector":"SingleAnswer","Configuration":{"QuestionDescriptionOption":"UseText","TextPosition":"inline","ChoiceColumnWidth":25,"RepeatHeaders":"none","WhiteSpace":"OFF","MobileFirst":true},"QuestionDescription":"Indicate to what extent you identify with the following feelings today:","Choices":{"1":{"Display":"Aggressive"},"2":{"Display":"Agonized"},"3":{"Display":"Anxious"},"4":{"Display":"Arrogant"},"5":{"Display":"Bored"},"6":{"Display":"Interested"},"7":{"Display":"Shocked"},"8":{"Display":"Smug"},"9":{"Display":"Miserable"},"10":{"Display":"Regretful"},"11":{"Display":"Relieved"},"12":{"Display":"Paranoid"},"13":{"Display":"Perplexed"},"14":{"Display":"Sheepish"}},"ChoiceOrder":[1,2,3,4,5,6,7,8,9,10,11,12,13,14],"Validation":{"Settings":{"ForceResponse":"OFF","ForceResponseType":"ON","Type":"None"}},"GradingData":[],"Language":[],"Answers":{"1":{"Display":"Not at all"},"2":{"Display":"Somewhat"},"3":{"Display":"Strongly"}},"AnswerOrder":["1","2","3"],"ChoiceDataExportTags":false,"QuestionID":"QID3"},"Responses":{"Q3_1":[2,1,3,2,2,1,2,1,1,3,3,2,1,3,3,1,3,3,1,1,2,1,"NA",2,3,1,1,"NA",2,"NA",1,2,3,2,2,"NA","NA",3,"NA","NA","NA",2,3,1,2,3],"Q3_2":[2,3,2,1,1,1,2,1,3,1,2,3,3,3,1,3,1,3,3,1,2,"NA","NA","NA","NA","NA",1,"NA",2,"NA",1,1,1,3,"NA",1,"NA",2,"NA","NA",1,2,1,3,1,1],"Q3_3":[2,2,2,2,1,1,3,1,2,3,2,1,2,3,1,2,3,3,1,1,1,"NA",2,2,"NA","NA",3,"NA","NA","NA",1,3,1,"NA",2,1,"NA","NA",1,2,"NA",2,2,2,3,1],"Q3_4":[3,3,2,1,1,1,3,3,1,2,1,1,1,2,3,3,3,1,2,2,3,2,1,1,"NA",2,"NA","NA","NA","NA","NA",2,"NA",3,"NA","NA","NA",1,1,"NA","NA",1,1,2,1,1],"Q3_5":[3,2,3,2,2,2,3,3,2,3,2,3,1,3,1,1,1,2,3,1,2,2,"NA","NA",1,2,"NA",1,1,1,"NA","NA","NA",1,"NA",1,"NA","NA",2,"NA","NA",1,1,3,1,1],"Q3_6":[3,3,2,1,1,2,3,3,1,1,1,2,1,3,3,2,2,3,2,3,2,2,"NA","NA",3,1,"NA","NA","NA","NA",3,3,"NA",2,"NA","NA",3,3,"NA",3,"NA",1,1,1,3,3],"Q3_7":[2,1,2,2,2,3,1,1,2,3,1,3,1,2,3,3,2,1,1,3,3,1,"NA","NA",2,"NA",1,"NA",1,2,1,"NA","NA","NA","NA","NA","NA","NA","NA",3,1,1,1,2,2,1],"Q3_8":[1,2,1,3,3,1,2,1,2,2,3,3,3,3,2,3,1,2,2,1,3,2,2,"NA","NA","NA","NA",2,"NA","NA",1,1,3,3,3,3,"NA","NA",3,"NA","NA",3,1,3,2,2],"Q3_9":[2,2,1,3,1,2,3,1,3,1,1,3,3,3,2,2,3,3,2,2,3,2,2,1,3,2,"NA","NA","NA","NA",2,"NA","NA",1,1,2,"NA",1,"NA","NA",3,3,3,1,3,1],"Q3_10":[1,2,3,3,3,1,1,3,1,1,1,3,1,1,1,1,2,1,2,1,2,"NA",3,"NA","NA",1,"NA","NA",1,"NA",2,"NA","NA","NA",1,1,"NA","NA","NA","NA","NA",3,1,1,3,3],"Q3_11":[3,1,2,1,1,1,3,2,2,2,3,1,3,3,3,2,3,2,2,3,3,"NA",1,"NA",1,"NA","NA","NA","NA","NA","NA","NA","NA",3,"NA","NA",3,"NA","NA",1,"NA",2,3,1,3,2],"Q3_12":[1,2,3,2,2,3,3,1,1,1,1,1,2,1,3,1,1,2,1,1,3,"NA",3,"NA","NA",3,3,"NA","NA","NA","NA",2,"NA",2,"NA","NA","NA","NA","NA","NA","NA",1,3,3,3,3],"Q3_13":[2,2,1,2,2,1,1,3,2,2,3,3,3,1,1,2,2,2,2,2,1,"NA","NA","NA",3,"NA","NA","NA","NA","NA",1,2,"NA",3,3,1,3,3,"NA","NA","NA",2,1,3,1,1],"Q3_14":[2,2,3,1,1,1,3,3,1,3,3,1,1,2,1,2,1,3,2,3,3,"NA",2,1,"NA","NA","NA",3,2,2,3,1,3,3,"NA","NA","NA",3,2,2,"NA",3,1,2,2,1]},"Table":{"Choices":{"1":"Aggressive","2":"Agonized","3":"Anxious","4":"Arrogant","5":"Bored","6":"Interested","7":"Shocked","8":"Smug","9":"Miserable","10":"Regretful","11":"Relieved","12":"Paranoid","13":"Perplexed","14":"Sheepish"},"Not at all":{"1":"34.2%","2":"48.6%","3":"36.1%","4":"47.1%","5":"42.9%","6":"28.6%","7":"44.1%","8":"25.0%","9":"29.7%","10":"56.2%","11":"29.0%","12":"38.7%","13":"32.4%","14":"31.6%"},"Somewhat":{"1":"34.2%","2":"22.9%","3":"41.7%","4":"26.5%","5":"31.4%","6":"25.7%","7":"32.4%","8":"33.3%","9":"32.4%","10":"15.6%","11":"29.0%","12":"22.6%","13":"38.2%","14":"31.6%"},"Strongly":{"1":"31.6%","2":"28.6%","3":"22.2%","4":"26.5%","5":"25.7%","6":"45.7%","7":"23.5%","8":"41.7%","9":"37.8%","10":"28.1%","11":"41.9%","12":"38.7%","13":"29.4%","14":"36.8%"},"N":{"1":"38","2":"35","3":"36","4":"34","5":"35","6":"35","7":"34","8":"36","9":"37","10":"32","11":"31","12":"31","13":"34","14":"38"}}}],[{"SurveyID":"SV_1GoZ6756ZYvbMyh","Element":"SQ","PrimaryAttribute":"QID4","SecondaryAttribute":"Tell us about how you feel using three random words, bruh:","TertiaryAttribute":null,"Payload":{"QuestionText":"Tell us about how you feel using three random words, bruh:","DefaultChoices":false,"DataExportTag":"Q4","QuestionType":"TE","Selector":"FORM","Configuration":{"QuestionDescriptionOption":"UseText"},"QuestionDescription":"Tell us about how you feel using three random words, bruh:","Choices":{"1":{"Display":"Feeling 1"},"2":{"Display":"Feeling 2"},"3":{"Display":"Feeling 3"}},"ChoiceOrder":["1","2","3"],"Validation":{"Settings":{"ForceResponse":"OFF","ForceResponseType":"ON","Type":null}},"GradingData":[],"Language":[],"QuestionID":"QID4"},"Responses":{"Q4_1_TEXT":["bruh","Est ab aenean mattis? Fringilla pede pede quis arcu fusce.","Luctus etiam lectus orci. Nibh venenatis dapibus sodales a. Ipsum nec.","Platea ligula. Potenti maecenas volutpat ultricies tempus consequat. Rutrum luctus. Nunc.","Id dolor ultricies erat per porttitor atque id nunc, rutrum commodo.","At! Gravida wisi? Platea dapibus sem euismod. Vitae pede dictumst.","Etiam accusamus posuere augue eu quis malesuada vestibulum? Vulputate! Dui donec.","Felis convallis wisi tincidunt mi convallis? Cursus dui dui. Convallis pretium wisi potenti? Urna convallis.","Faucibus. Blandit cursus ipsum vivamus dolorem ligula nullam magnis. Cursus. Magnis tincidunt eleifend.","Erat bibendum gravida! Proin convallis. Massa nec tempus etiam! Odio.","Bibendum? Imperdiet eleifend, facilisis vel nulla vel elit ultrices tellus mauris id mauris proin porta.","Cras aenean massa! Interdum tincidunt et. Ante suscipit posuere. Sollicitudin nullam ridiculus.","Dictumst vitae gravida, integer per? Lorem euismod. Turpis wisi euismod atque bibendum suscipit.","Primis? Eget ultricies tempor dapibus? Scelerisque pretium ultricies ligula atque euismod? Neque interdum. Enim consectetuer.","Nibh nunc posuere integer molestie! Porta etiam mattis ab tellus.","Egestas, vitae at laoreet tellus nonummy purus leo fusce ac ridiculus.","Gravida eget? Aliquam tellus euismod dignissim imperdiet lectus! Atque vulputate.","Wisi montes. Tempor? Ab vehicula suscipit pellentesque potenti risus donec.","Orci eu sapien tellus mattis ultrices eleifend faucibus fermentum eros amet luctus quam nulla.","Cursus proin donec dictumst! Suscipit faucibus? In molestie accusamus. Fusce pellentesque, orci neque.","Dolor in sapien! Donec vulputate quis euismod, enim cursus enim lorem viverra dui.","","Potenti proin gravida fermentum, pellentesque morbi natoque felis. Sagittis tincidunt. Morbi tempus dolorem! Dictumst ultricies.","Cursus. Lorem diam diam ac orci turpis, tempora scelerisque placerat orci tortor quis culpa.","","Ab ipsum. Dui? Iaculis. Elementum amet vestibulum, sed gravida molestie potenti posuere temporibus consequat suscipit.","Fermentum ab vel fermentum consectetuer. Enim, facilisis vulputate. Felis dolorem euismod primis justo.","Nibh blandit elementum quis leo platea, ullamcorper, pellentesque? Donec magna.","Magnis fermentum ut egestas erat ante velit. Fusce consectetuer luctus primis placerat. Vulputate.","Nulla euismod vivamus nunc urna? Consequat nunc iaculis imperdiet fermentum aliquet ligula.","Purus rhoncus dolorem blandit atque suscipit. Aliquam tincidunt rutrum sed! Scelerisque tempora porta erat volutpat.","","","","Donec, vulputate aenean tempus per auctor natoque, iaculis magnis? Molestie arcu. Neque auctor. Etiam sagittis.","","","Tincidunt gravida magna justo quis dolorem purus mi dapibus ullamcorper cursus. Massa culpa primis. Pretium.","","Luctus pellentesque malesuada porta lacus phasellus ut curabitur fusce nulla? Per temporibus vivamus.","","Amet eleifend quam praesent vehicula! Sagittis at, scelerisque quis sapien duis velit. Arcu et faucibus.","Magna urna integer venenatis facilisi donec aliquam. Odio nullam duis. Felis molestie. Blandit.","Felis non nec proin? Ac laoreet nunc. Ridiculus aliquam eleifend volutpat aenean integer pede.","Ullamcorper? Viverra euismod temporibus sodales consequat aliquet tincidunt a eleifend molestie.","Luctus vel temporibus, facilisis ultrices in massa quam. Elementum convallis accusamus etiam."],"Q4_2_TEXT":["brah","Ab potenti? Enim. Leo? Donec. Eleifend purus ipsum. Aenean posuere fusce? Vel.","A vestibulum nonummy. Amet felis gravida massa faucibus. Est lectus.","Scelerisque eleifend velit vehicula tincidunt! Neque etiam, per! Mattis vulputate praesent ultrices.","Laoreet duis tortor ultrices! Turpis fusce dictumst metus pellentesque aliquet.","Sagittis magnis vulputate metus. Primis lectus tempora nibh malesuada curabitur proin etiam, proin ut morbi.","Magnis felis proin eleifend! Eros non. Curabitur sem euismod orci facilisis elit.","Ante? Nonummy quis, tortor cras! Fusce atque at venenatis atque mi vulputate posuere luctus.","Posuere nulla culpa auctor non ante vel leo accumsan? Mattis! Porta.","Luctus. Natoque montes nullam ultrices mi ullamcorper vulputate mauris, ab. Pellentesque pharetra aenean montes.","Id donec, erat ut nunc montes porttitor per sagittis? Primis curabitur! Platea posuere metus.","Venenatis lacus nonummy iaculis. Lorem? Purus. Accumsan. Auctor aliquet fermentum? Dapibus.","Pretium mi, iaculis nibh suspendisse luctus? Ut vel. Sollicitudin accumsan atque phasellus.","Accumsan vestibulum etiam sed egestas aliquam magnis magnis id justo.","Sagittis? Suscipit molestie praesent montes diam. Temporibus pede. Placerat! Vitae leo non luctus.","A per scelerisque elementum diam molestie. Nunc primis quis ante auctor.","Non ab! Ut auctor venenatis. Arcu enim metus augue porttitor nulla commodo eleifend.","Ipsum neque tortor morbi lectus praesent praesent suscipit neque atque scelerisque risus ultrices purus fusce.","Aliquet! Platea blandit eleifend cursus dignissim odio! Eleifend suspendisse enim, facilisi volutpat curabitur et! Luctus.","Rutrum risus ac eu arcu aenean montes, vel. Felis. Imperdiet rutrum, egestas scelerisque nibh mi.","Eleifend pretium mi. Eu. Mauris arcu etiam neque luctus porta sit.","Integer cras platea elementum natoque pretium enim sapien, tortor platea dolorem vivamus. Dolor.","","","","","","","Facilisi tempor odio, montes sodales proin! Commodo! Curabitur tincidunt convallis placerat.","Ultrices fermentum vestibulum a curabitur ullamcorper magnis quam iaculis dignissim.","Erat velit per! Purus rhoncus ligula montes sagittis elementum fusce.","Enim. Lorem mauris atque eros lorem. Interdum per vitae convallis eu.","Vivamus accusamus etiam sodales molestie vel diam consequat felis ut donec non, dictumst. Ut tortor.","","Cursus est. Vehicula imperdiet est sapien etiam pretium! Diam! Mi est.","","Porttitor. Platea auctor, sapien. Etiam potenti. Tincidunt, imperdiet duis metus eu pharetra. Nonummy felis mauris.","","Fringilla nulla id. Wisi maecenas viverra convallis ligula nec consectetuer sollicitudin.","Est ab wisi mattis risus pellentesque felis tincidunt, euismod sed venenatis tempor accusamus.","Phasellus vulputate vestibulum fringilla accumsan cras? Wisi pellentesque commodo primis mattis, suscipit quam aliquam.","Eget et eros? Est, dolorem, rhoncus ullamcorper suscipit venenatis, ullamcorper? Vitae ac ridiculus.","Fermentum dui? Lorem convallis commodo culpa pretium. Wisi cursus non praesent purus. Tempora faucibus.","Leo malesuada? Aliquet felis. Fringilla platea vivamus viverra quam. Viverra accusamus vivamus. Per tempora.","Consequat massa. Et eleifend? Vivamus. Est wisi? Ultricies lorem erat.","Venenatis malesuada augue tempor. Pretium sit, primis tempora diam imperdiet morbi lorem."],"Q4_3_TEXT":["bro-man","Culpa maecenas convallis bibendum nulla maecenas risus lacus, curabitur suspendisse imperdiet tempora, donec.","Pharetra accumsan at dui nec vehicula viverra nec, magnis ligula.","Ullamcorper? Fusce non dictumst accusamus. Ultrices turpis proin, dui nulla. Vel.","Ridiculus malesuada magnis convallis blandit proin massa dolorem! Fringilla risus etiam tortor at neque.","Montes. Mi! Nibh, lacus malesuada blandit! Nunc vestibulum mi dolor temporibus diam sollicitudin magnis.","Elementum consequat tempor potenti? Ipsum temporibus ridiculus. Felis ipsum sed interdum, accumsan.","Volutpat eget iaculis porttitor tempus viverra sed urna suscipit augue sagittis? Etiam.","Aenean. Urna. Dapibus commodo natoque luctus nonummy. Pharetra at aliquam velit.","Auctor amet dolorem facilisis integer mauris massa eu orci per! Risus luctus venenatis scelerisque vel.","Felis proin maecenas blandit velit cras bibendum fringilla rhoncus! Mauris nec vehicula felis.","Fringilla per temporibus! Dolor primis tempus accusamus, risus? Scelerisque tempora venenatis facilisi ab, ullamcorper iaculis.","Vivamus pretium cras! Dui donec dolorem, convallis mi lacus posuere fringilla elit at eleifend duis.","Pretium. Vestibulum facilisis! Bibendum! Consectetuer tempus vel morbi primis. Phasellus elit, per volutpat lacus.","Aenean morbi arcu. Nonummy orci. Sem et velit tempora, ut, et accumsan.","Aenean tortor suscipit id? Sapien tempora nullam, sagittis at sagittis sit curabitur tempora.","Eros tellus at ab sagittis accumsan montes! Nunc eget etiam magnis.","Nulla sagittis. Placerat rhoncus vitae consectetuer vulputate? Tempus orci convallis tempus suscipit fusce lectus malesuada.","Nibh amet dapibus amet vehicula massa quis fusce faucibus praesent velit! Per posuere justo interdum.","Aliquam eu ridiculus nec dictumst! Pretium! Risus at risus rutrum commodo.","Dolorem egestas? Leo tempus. Euismod dapibus ullamcorper phasellus tempor placerat? Duis convallis. Rutrum arcu consequat.","Pede eu, ligula diam donec scelerisque donec commodo eros nonummy. Elit. Proin, purus dictumst.","","Eros elementum sagittis rutrum ullamcorper nonummy dui morbi magnis blandit dignissim.","Convallis aenean fringilla suscipit amet sodales! Sed ultrices porta orci convallis dignissim a.","","Tempor. At? Ac accumsan mi. Sed mauris. Massa. Tellus morbi sapien commodo! Atque velit vulputate.","","","","Fringilla amet ut! Id! Phasellus vehicula, volutpat. Eget vulputate non accumsan.","","","","","","Proin felis risus sem imperdiet placerat viverra? Potenti cras turpis augue odio consequat placerat.","","","Justo scelerisque cras ab. Erat erat, ultricies sagittis consequat aliquet duis commodo. Vivamus enim.","","Dignissim temporibus nullam montes a auctor, tellus, faucibus auctor vel diam. Cras etiam.","Orci! Porta eros? Porttitor dui neque accusamus ut commodo ipsum donec. Eleifend atque.","Nullam consectetuer integer nec ultricies sodales mattis iaculis mauris, natoque.","Erat sodales turpis nunc? Blandit! Integer at montes? Porta purus mauris non.","Ut porttitor tempor tempora ultrices etiam vulputate lorem, malesuada dapibus, suscipit venenatis neque tempor."]}}],[{"SurveyID":"SV_1GoZ6756ZYvbMyh","Element":"SQ","PrimaryAttribute":"QID5","SecondaryAttribute":"How does the size of this ugly matrix question make you feel?","TertiaryAttribute":null,"Payload":{"QuestionText":"How does the size of this ugly matrix question make you feel?","DefaultChoices":false,"DataExportTag":"Q5","QuestionType":"Matrix","Selector":"Likert","SubSelector":"SingleAnswer","Configuration":{"QuestionDescriptionOption":"UseText","TextPosition":"inline","ChoiceColumnWidth":25,"RepeatHeaders":"none","WhiteSpace":"OFF","MobileFirst":true},"QuestionDescription":"How does the size of this ugly matrix question make you feel?","Choices":{"1":{"Display":"Awful"},"2":{"Display":"Happy to be alive"},"3":{"Display":"Somewhere in between awful and happy to be alive"}},"ChoiceOrder":["1","2","3"],"Validation":{"Settings":{"ForceResponse":"OFF","ForceResponseType":"ON","Type":"None"}},"GradingData":[],"Language":[],"Answers":{"1":{"Display":"Totally not at all, like what are you talking about?"},"2":{"Display":"I mean, I guess? I don't know, I don't think I can relate to the question very well."},"3":{"Display":"What're you talking about?"},"4":{"Display":"Kinda?"},"5":{"Display":"I feel that, like only a little though"},"6":{"Display":"Why are there so many options to this question?"},"7":{"Display":"Because it's a made up survey, bruh"},"8":{"Display":"Do you even survey?"},"9":{"Display":"Who knows what's going on anymore"},"10":{"Display":"10 columns? yeahhhh, that's what i'm talkin' about, mannnnnn"}},"AnswerOrder":[1,2,3,4,5,6,7,8,9,10],"ChoiceDataExportTags":false,"QuestionID":"QID5","DisplayLogic":{"0":{"0":{"LogicType":"Question","QuestionID":"QID1","QuestionIsInLoop":"no","ChoiceLocator":"q://QID1/SelectableChoice/19","Operator":"Displayed","QuestionIDFromLocator":"QID1","LeftOperand":"q://QID1/ChoiceDisplayed/19","Type":"Expression","Description":"<span class=\"ConjDesc\">If</span> <span class=\"QuestionDesc\">Indicate how you feel today</span> <span class=\"LeftOpDesc\">Surprised</span> Is <span class=\"OpDesc\">Displayed</span> "},"Type":"If"},"Type":"BooleanExpression","inPage":false}},"Responses":{"Q5_1":[1,5,9,4,10,6,6,3,5,9,5,4,3,6,8,8,4,4,1,7,9,7,2,8,7,3,7,"NA",2,10,4,"NA",5,9,8,7,2,"NA","NA",6,5,10,5,4,4,10],"Q5_2":[5,9,3,10,1,1,4,9,8,7,3,6,1,4,4,8,3,4,4,6,2,"NA","NA",3,"NA",5,6,6,3,"NA","NA",6,4,"NA","NA","NA","NA","NA","NA",10,1,4,10,9,6,6],"Q5_3":[6,6,3,8,1,7,2,5,2,1,5,2,5,4,8,1,9,10,1,7,10,"NA",2,4,6,"NA",1,"NA","NA",8,"NA","NA",2,8,"NA",9,"NA",1,"NA",3,"NA",7,1,3,8,8]},"Table":{"Choices":{"1":"Awful","2":"Happy to be alive","3":"Somewhere in between awful and happy to be alive"},"Totally not at all, like what are you talking about?":{"1":"4.8%","2":"11.4%","3":"19.4%"},"I mean, I guess? I don't know, I don't think I can relate to the question very well.":{"1":"7.1%","2":"2.9%","3":"13.9%"},"What're you talking about?":{"1":"7.1%","2":"14.3%","3":"8.3%"},"Kinda?":{"1":"16.7%","2":"20.0%","3":"5.6%"},"I feel that, like only a little though":{"1":"14.3%","2":"5.7%","3":"8.3%"},"Why are there so many options to this question?":{"1":"9.5%","2":"20.0%","3":"8.3%"},"Because it's a made up survey, bruh":{"1":"11.9%","2":"2.9%","3":"8.3%"},"Do you even survey?":{"1":"9.5%","2":"5.7%","3":"16.7%"},"Who knows what's going on anymore":{"1":"9.5%","2":"8.6%","3":"5.6%"},"10 columns? yeahhhh, that's what i'm talkin' about, mannnnnn":{"1":"9.5%","2":"8.6%","3":"5.6%"},"N":{"1":"42","2":"35","3":"36"}}}]]},{"Type":"Standard","SubType":"","Description":"Here, have an empty block. Do with this what you may.","ID":"BL_3pJvuUR5tQEqMMl"},{"Type":"Standard","SubType":"","Description":"I want to be a lego brick when I grow out of my larval-block stage.","ID":"BL_3yBSfuCGLZjFaSx","BlockElements":[[{"SurveyID":"SV_1GoZ6756ZYvbMyh","Element":"SQ","PrimaryAttribute":"QID7","SecondaryAttribute":"What do you think about legos? ","TertiaryAttribute":null,"Payload":{"QuestionText":"What do you think about legos? ","DefaultChoices":false,"DataExportTag":"Q7","QuestionType":"TE","Selector":"ESTB","Configuration":{"QuestionDescriptionOption":"UseText","InputWidth":680},"QuestionDescription":"What do you think about legos? ","Validation":{"Settings":{"ForceResponse":"OFF","ForceResponseType":"ON","Type":"None"}},"GradingData":[],"Language":[],"QuestionID":"QID7"},"Responses":{"Q7":["legos are pretty dope","Cras! Et. Convallis neque montes? Ab nec sed atque turpis dignissim.","Pharetra egestas accusamus elit vel metus euismod vitae luctus eu mi platea. Porttitor tempus. Purus.","Ut suscipit sem venenatis atque curabitur amet proin? Orci pede.","Ridiculus aenean? Integer sagittis vitae sit dolorem phasellus felis risus est.","Rhoncus turpis pede tincidunt! Interdum cursus purus consequat vehicula. Fringilla nunc culpa.","Suspendisse pharetra molestie. A a cursus blandit, montes nunc consectetuer facilisis proin.","Pretium per auctor? Nibh dapibus faucibus sapien? Risus, augue, ut, praesent purus augue consectetuer facilisi.","Bibendum culpa. Fringilla. Ligula. Sed consectetuer viverra diam euismod malesuada.","Placerat posuere ridiculus pede porttitor atque fusce urna commodo magnis nibh nullam. Morbi.","Dui etiam per, at ligula. Integer dignissim ab. Ridiculus gravida est dui convallis et.","Vivamus pede laoreet placerat. Nunc. Dictumst faucibus non porta nibh sagittis nulla facilisis.","Cursus mi commodo mi nibh! Odio auctor. Tempor mi accusamus aliquam.","Nonummy sagittis leo ac natoque. Lacus dolorem lectus pede scelerisque dolor.","Urna et purus sagittis vel. Purus mauris morbi auctor purus. Tincidunt wisi cras gravida. Est.","Cras quis? Pede nonummy dictumst tellus enim montes sit? Eu, atque.","Ipsum. Suscipit tortor, curabitur euismod. Curabitur. Vel faucibus cursus platea donec curabitur pellentesque.","Magnis dignissim vehicula laoreet porttitor maecenas primis interdum diam, facilisi.","Dapibus laoreet, dapibus. Augue turpis? Pellentesque duis amet sollicitudin. Phasellus facilisis nonummy.","Ipsum sed luctus facilisi tempus tempus wisi justo, eu nibh per fringilla pretium interdum accumsan.","Curabitur ridiculus pede nonummy interdum metus aliquet? Ultrices fusce, nonummy primis.","Laoreet imperdiet vel commodo, orci interdum luctus suscipit quam ultricies platea et.","Curabitur molestie euismod. Quis molestie id faucibus pharetra nonummy faucibus, dolor posuere ut vivamus sagittis.","Aenean dolorem montes lectus commodo a eu auctor. Volutpat vel tortor dictumst fusce euismod.","Ligula nec? Sem, curabitur in ultricies? Aliquam malesuada tempus mauris natoque.","Vel risus, convallis? Imperdiet? Felis quis sagittis cras. Amet magnis aliquet dolorem. Aenean.","Arcu, augue vel primis non tempor quam. Nibh sapien est.","Tellus est! Lorem ac? Consectetuer velit justo atque nec vestibulum eros.","Enim volutpat euismod nunc. Justo est. Quam elementum ullamcorper nibh dignissim etiam. Lectus porta platea.","Dictumst tortor velit fusce tempora aenean donec cursus. Dapibus. Aliquet donec porttitor auctor! Est! Tellus.","Tellus ut, eros molestie iaculis vitae nunc integer tincidunt rutrum non auctor.","Ut. Tortor sollicitudin! Ultrices fermentum vestibulum montes mi urna magna volutpat.","Amet turpis nec tempora, scelerisque nulla bibendum ac egestas vivamus tempor. Aenean dolor vestibulum! Ac.","Tempus? Luctus primis praesent ab lectus sollicitudin sed ut sodales ante ullamcorper, erat.","Sem urna. Dolor atque enim ipsum risus est, velit suscipit nec suscipit natoque.","Facilisi atque porttitor sollicitudin! Sollicitudin risus! Facilisi, culpa ab metus felis dictumst! Laoreet primis commodo.","Viverra magna ridiculus iaculis scelerisque suspendisse phasellus? Sed laoreet! Per. Quam venenatis? Ipsum magnis.","Tellus. Facilisi pharetra montes massa. Iaculis proin cursus risus primis! Lacus culpa. Elit fringilla! Non.","Malesuada rutrum vivamus. Dignissim vestibulum fringilla ut faucibus vestibulum? Elit.","Culpa, culpa ullamcorper. Donec sem luctus integer ab tempor vivamus curabitur justo aliquet ante.","Volutpat pede nec ridiculus a platea! Faucibus? Vivamus ullamcorper culpa.","Enim est purus. Porta arcu porttitor! Dignissim! Nunc risus odio.","Placerat convallis malesuada euismod vel, dapibus est duis potenti. Sit nec tincidunt molestie.","Lectus tellus nonummy aliquet tempora! Dolorem aliquet vehicula amet metus.","Volutpat auctor sit consequat elit vel eget, arcu facilisi. Tempora? Molestie metus accusamus? Tempora.","Diam mi wisi malesuada primis sem. Scelerisque nullam consequat? Eu."]}}],[{"SurveyID":"SV_1GoZ6756ZYvbMyh","Element":"SQ","PrimaryAttribute":"QID8","SecondaryAttribute":"Descriptive text boxes are people too!\u00a0 \ud83c\udf79\ud83c\udf77","TertiaryAttribute":null,"Payload":{"QuestionText":"Descriptive text boxes are people too\ufffd\ufffd\ufffd\ufffd","DefaultChoices":false,"DataExportTag":"Q8","QuestionType":"DB","Selector":"TB","Configuration":{"QuestionDescriptionOption":"UseText"},"QuestionDescription":"Descriptive text boxes are people too!\u00a0 \ud83c\udf79\ud83c\udf77","ChoiceOrder":[],"Validation":{"Settings":{"Type":"None"}},"GradingData":[],"Language":[],"QuestionID":"QID8"},"Responses":{"Q8":[1,1,1,1,1,1,1,1,1,1,1,1,1,1,1,1,1,1,1,1,1,1,1,1,1,1,1,1,1,1,1,1,1,1,1,1,1,1,1,1,1,1,1,1,1,1]}}]]},{"Type":"Standard","SubType":"","Description":"\ud83d\udc11 Sheep are chill, man","ID":"BL_40KFwTfx25lvCcJ","BlockElements":[[{"SurveyID":"SV_1GoZ6756ZYvbMyh","Element":"SQ","PrimaryAttribute":"QID9","SecondaryAttribute":"Rank the following things, man","TertiaryAttribute":null,"Payload":{"QuestionText":"Rank the following things, man","DefaultChoices":false,"DataExportTag":"Q9","QuestionID":"QID9","QuestionType":"RO","Selector":"DND","SubSelector":"TX","Configuration":{"QuestionDescriptionOption":"UseText"},"QuestionDescription":"Rank the following things, man","Choices":{"1":{"Display":"thing1"},"2":{"Display":"thing2"},"3":{"Display":"thing3"}},"ChoiceOrder":["1","2","3"],"Validation":{"Settings":{"ForceResponse":"OFF","Type":"None"}},"GradingData":[],"Language":[]},"Responses":{"Q9_1":[3,3,2,3,1,2,2,1,2,1,1,2,3,3,2,2,2,2,1,1,1,1,3,1,1,2,3,2,2,1,1,3,1,1,2,2,2,1,3,3,1,2,3,2,3,3],"Q9_2":[2,2,1,1,3,1,3,2,3,3,2,3,1,1,3,1,3,3,2,3,3,3,1,3,3,1,1,3,1,2,3,2,2,3,3,1,3,3,1,1,3,1,2,1,1,1],"Q9_3":[1,1,3,2,2,3,1,3,1,2,3,1,2,2,1,3,1,1,3,2,2,2,2,2,2,3,2,1,3,3,2,1,3,2,1,3,1,2,2,2,2,3,1,3,2,2]}}],[{"SurveyID":"SV_1GoZ6756ZYvbMyh","Element":"SQ","PrimaryAttribute":"QID10","SecondaryAttribute":"This is a bipolar matrix to test with!","TertiaryAttribute":null,"Payload":{"QuestionText":"This is a bipolar matrix to test with!","DefaultChoices":false,"DataExportTag":"Q10","QuestionType":"Matrix","Selector":"Bipolar","Configuration":{"QuestionDescriptionOption":"UseText","TextPosition":"inline","ChoiceColumnWidth":25,"MobileFirst":true},"QuestionDescription":"This is a bipolar matrix to test with!","Choices":{"1":{"Display":"Click to write Statement 1:Boop"},"2":{"Display":"bo:meh"},"3":{"Display":"gra:ahhhh"},"4":{"Display":"who knows:woooooo"}},"ChoiceOrder":[1,2,3,4],"Validation":{"Settings":{"ForceResponse":"OFF","ForceResponseType":"ON","Type":"None"}},"GradingData":[],"Language":[],"Answers":{"1":{"Display":"1"},"2":{"Display":"2"},"3":{"Display":"3"}},"AnswerOrder":["1","2","3"],"AnswerColumns":3,"ChoiceDataExportTags":false,"QuestionID":"QID10"},"Responses":{"Q10_1":["NA","NA","NA","NA","NA","NA","NA","NA","NA","NA","NA","NA","NA","NA","NA","NA","NA","NA","NA","NA","NA","NA","NA","NA","NA","NA","NA","NA","NA","NA","NA","NA","NA","NA","NA","NA","NA","NA","NA","NA","NA",3,2,1,2,2],"Q10_2":["NA","NA","NA","NA","NA","NA","NA","NA","NA","NA","NA","NA","NA","NA","NA","NA","NA","NA","NA","NA","NA","NA","NA","NA","NA","NA","NA","NA","NA","NA","NA","NA","NA","NA","NA","NA","NA","NA","NA","NA","NA",1,2,3,2,2],"Q10_3":["NA","NA","NA","NA","NA","NA","NA","NA","NA","NA","NA","NA","NA","NA","NA","NA","NA","NA","NA","NA","NA","NA","NA","NA","NA","NA","NA","NA","NA","NA","NA","NA","NA","NA","NA","NA","NA","NA","NA","NA","NA",1,1,1,1,3],"Q10_4":["NA","NA","NA","NA","NA","NA","NA","NA","NA","NA","NA","NA","NA","NA","NA","NA","NA","NA","NA","NA","NA","NA","NA","NA","NA","NA","NA","NA","NA","NA","NA","NA","NA","NA","NA","NA","NA","NA","NA","NA","NA",3,2,2,2,1]},"Table":{"left_choices":{"1":"Click to write Statement 1","2":"bo","3":"gra","4":"who knows"},"1":{"1":"20.0%","2":"20.0%","3":"80.0%","4":"20.0%"},"2":{"1":"60.0%","2":"60.0%","3":"0.0%","4":"60.0%"},"3":{"1":"20.0%","2":"20.0%","3":"20.0%","4":"20.0%"},"right_choices":{"1":"Boop","2":"meh","3":"ahhhh","4":"woooooo"}}}]]}]}
